AUTHORS
LICENSE
MANIFEST.in
README.rst
setup.py
sparx/__init__.py
sparx/__version__.py
sparx.egg-info/PKG-INFO
sparx.egg-info/SOURCES.txt
sparx.egg-info/dependency_links.txt
sparx.egg-info/requires.txt
sparx.egg-info/top_level.txt
sparx/connect/__init__.py
sparx/preprocess/__init__.py
sparx/preprocess/stopwords.py
sparx/stats/__init__.py
sparx/text/__init__.py
tests/__init__.py
tests/test_preprocess.py