Metadata-Version: 1.1
Name: sparx
Version: 0.0.2
Summary: Sparx is a simplified data munging, wrangling and preparation library
Home-page: http://sparx.cleverinsight.co
Author: Bastin Robins J
Author-email: robin@cleverinsight.co
License: BSD
Keywords: sparx data-science data-analysis data-preprocessing data-wrangling data-cleaning
Platform: UNKNOWN
Classifier: Development Status :: 3 - Alpha
Classifier: Environment :: Console
Classifier: Intended Audience :: Developers
Classifier: Intended Audience :: Information Technology
Classifier: License :: OSI Approved :: BSD License
Classifier: Operating System :: OS Independent
Classifier: Natural Language :: English
Classifier: Programming Language :: Python :: 2
Classifier: Programming Language :: Python :: 2.7
Classifier: Programming Language :: Python :: 3
Classifier: Programming Language :: Python :: 3.4
Classifier: Programming Language :: Python :: 3.5
